McCalcTools/McCalcTools.py
McCalcTools/__init__.py
mccalctools-0.4.1.dist-info/licenses/LICENSE
mccalctools-0.4.1.dist-info/METADATA
mccalctools-0.4.1.dist-info/WHEEL
mccalctools-0.4.1.dist-info/top_level.txt
mccalctools-0.4.1.dist-info/RECORD
