Metadata-Version: 2.4
Name: McCalcTools
Version: 0.4.1
Summary: Minecraft utility calculations for blocks, chunks, and more
Author-email: Buildercgr <buildercgr@outlook.com>
License: MIT License
Requires-Python: >=3.7
License-File: LICENSE
Dynamic: license-file
